objectrest/__info__.py
objectrest/__init__.py
objectrest/base_requests.py
objectrest/decorators.py
objectrest/exceptions.py
objectrest/json_handler.py
objectrest/object_handler.py
objectrest/request_handler.py
objectrest/response.py
objectrest/session.py
objectrest/utils.py
tests/__init__.py
tests/object.py
tests/test_api_token_request_hander.py
tests/test_base_requests.py
tests/test_json_handler.py
tests/test_oauth_2_request_handler.py
tests/test_object_handler.py
tests/test_request_handler.py
objectrest-2.0.0.dist-info/LICENSE
objectrest-2.0.0.dist-info/METADATA
objectrest-2.0.0.dist-info/WHEEL
objectrest-2.0.0.dist-info/top_level.txt
objectrest-2.0.0.dist-info/RECORD
