Metadata-Version: 2.1
Name: objectrest
Version: 2.0.0
Summary: A Python package to handle REST API requests, JSON parsing, and pydantic object generation.
Home-page: https://github.com/nwithan8/objectrest
Author: Nate Harris
Author-email: n8gr8gbln@gmail.com
License: GNU General Public License v3 (GPLv3)
Download-URL: https://github.com/nwithan8/objectrest/archive/2.0.0.tar.gz
Keywords: API,REST,objects,pydantic,JSON,requests,OAuth2,token
Platform: UNKNOWN
Classifier: License :: OSI Approved :: GNU General Public License v3 (GPLv3)
Classifier: Development Status :: 4 - Beta
Classifier: Intended Audience :: Developers
Classifier: Topic :: Software Development :: Build Tools
Classifier: Programming Language :: Python :: 3
Classifier: Programming Language :: Python :: 3.7
Classifier: Programming Language :: Python :: 3.8
Classifier: Programming Language :: Python :: 3.9
Classifier: Topic :: Multimedia :: Video
Classifier: Topic :: Multimedia
Classifier: Topic :: Internet :: WWW/HTTP
Classifier: Operating System :: OS Independent
Requires-Python: >=3.7
Requires-Dist: requests (>=2.27.1)
Requires-Dist: requests-oauthlib (>=1.3.0)
Requires-Dist: httpx (==0.23.*)
Requires-Dist: oauthlib (==3.2.1)
Requires-Dist: proxlist (~=0.5.0)
Provides-Extra: dev
Requires-Dist: black ; extra == 'dev'
Requires-Dist: flake8 ; extra == 'dev'
Requires-Dist: pytest-cov (==3.*) ; extra == 'dev'
Requires-Dist: pytest-vcr (==1.*) ; extra == 'dev'
Requires-Dist: pytest (==7.*) ; extra == 'dev'
Requires-Dist: pydantic ; extra == 'dev'
Requires-Dist: requests (>=2.27.1) ; extra == 'dev'
Requires-Dist: requests-oauthlib (>=1.3.0) ; extra == 'dev'
Requires-Dist: httpx (==0.23.*) ; extra == 'dev'
Requires-Dist: oauthlib (==3.2.1) ; extra == 'dev'
Requires-Dist: proxlist (~=0.5.0) ; extra == 'dev'
